{"id":"e8b5e37d-7415-4714-b119-6d0b8053799e","title":"Заключение контракта с поставщиком в г. Евпатория (№1)","slug":"zaklyuchenie-kontrakta-s-postavschikom-v-g-evpatoriya-1-1","excerpt":"Подведены итоги очередного квартала: показатели превзошли план. Подробности — в нашем материале.","content":"## Заключение контракта с поставщиком\n\nПодведены итоги очередного квартала: показатели превзошли план. Объект расположен в городе Евпатория и реализован с применением современных строительных технологий.\n\nНад проектом работала команда из более чем 30 специалистов. Сроки реализации были соблюдены, а качество выполненных работ подтверждено независимой экспертизой.\n\n### Ключевые показатели\n\n- Общая площадь: 14756 м²\n- Срок работ: 19 мес.\n- Количество подрядчиков: 6\n\nМы благодарим всех партнёров и заказчиков за доверие. Впереди — новые амбициозные задачи.","imageId":"61013bd5-b54d-4d15-9cf9-49081541fbdb","published":true,"publishedAt":"2025-06-06T23:31:05.170Z","createdAt":"2026-05-11T23:31:05.172Z","updatedAt":"2026-05-11T23:31:05.172Z","image":{"id":"61013bd5-b54d-4d15-9cf9-49081541fbdb","createdAt":"2026-05-11T23:31:05.171Z","updatedAt":"2026-05-11T23:31:05.171Z","filename":"news-1.webp","originalName":"news-1.webp","mimeType":"image/webp","size":0,"path":"/seed/news-1.webp","url":"/projects/news-1-1200x800.jpg","uploadedById":null}}